shopyo_base/__init__.py
shopyo_base/info.json
shopyo_base/view.py
shopyo_base/templates/shopyo_base/main_base.html
shopyo_base/templates/shopyo_base/module_base.html
shopyo_base/templates/shopyo_base/nav_base.html
shopyo_base/templates/shopyo_base/blocks/default_styles.html
shopyo_base/templates/shopyo_base/blocks/flashed_messages.html
shopyo_base/templates/shopyo_base/blocks/footer.html
shopyo_base/templates/shopyo_base/blocks/macros.html
shopyo_base/templates/shopyo_base/blocks/resources.html
shopyo_base-1.4.0.dist-info/METADATA
shopyo_base-1.4.0.dist-info/WHEEL
shopyo_base-1.4.0.dist-info/top_level.txt
shopyo_base-1.4.0.dist-info/RECORD
